moltx/__init__.py
moltx/_version.py
moltx/datasets.py
moltx/models.py
moltx/nets.py
moltx/pipelines.py
moltx/tokenizers.py
moltx/data/spe_safe.txt
moltx/data/spe_smiles.txt
moltx/data/tks_safe.json
moltx/data/tks_smiles.json
moltx-2.0.0.dist-info/LICENSE
moltx-2.0.0.dist-info/METADATA
moltx-2.0.0.dist-info/WHEEL
moltx-2.0.0.dist-info/top_level.txt
moltx-2.0.0.dist-info/RECORD
