Metadata-Version: 2.1
Name: moltx
Version: 2.0.0
Summary: Molcule Transformer X Model
Author: Michael Ding
Author-email: yandy.ding@gmail.com
Keywords: molcule,AI,deep learning,transformer
Classifier: Environment :: Console
Classifier: Intended Audience :: Science/Research
Classifier: Operating System :: POSIX
Classifier: Programming Language :: Python
Classifier: Programming Language :: Python :: 3
Classifier: Development Status :: 5 - Production/Stable
Requires-Python: >=3.9
License-File: LICENSE
Requires-Dist: rdkit ~=2023.9.1
Requires-Dist: torch ~=2.1.0
